app/__init__.py
app/__main__.py
app/cli.py
app/collector.py
app/compare.py
app/db.py
app/main.py
app/models.py
app/parser.py
app/scheduler.py
app/utils.py
app/static/.gitkeep
app/templates/about.html
app/templates/base.html
app/templates/compare.html
app/templates/compare_result.html
app/templates/crons.html
app/templates/error.html
app/templates/host_detail.html
app/templates/hosts.html
app/templates/index.html
app/templates/job_detail.html
app/templates/jobs.html
mysql_awesome_stats_collector-1.0.26.dist-info/licenses/LICENSE
mysql_awesome_stats_collector-1.0.26.dist-info/METADATA
mysql_awesome_stats_collector-1.0.26.dist-info/WHEEL
mysql_awesome_stats_collector-1.0.26.dist-info/entry_points.txt
mysql_awesome_stats_collector-1.0.26.dist-info/top_level.txt
mysql_awesome_stats_collector-1.0.26.dist-info/RECORD
