Metadata-Version: 2.4
Name: mysql-awesome-stats-collector
Version: 1.0.26
Summary: MySQL Awesome Stats Collector - Collect and visualize MySQL diagnostics from multiple hosts
Author-email: MySQL Awesome Stats Collector <hello@kratik.dev>
Maintainer-email: MySQL Awesome Stats Collector <hello@kratik.dev>
License: MIT
Project-URL: Homepage, https://github.com/k4kratik/mysql-awesome-stats-collector
Project-URL: Repository, https://github.com/k4kratik/mysql-awesome-stats-collector
Project-URL: Documentation, https://github.com/k4kratik/mysql-awesome-stats-collector#readme
Project-URL: Bug Reports, https://github.com/k4kratik/mysql-awesome-stats-collector/issues
Keywords: mysql,diagnostics,monitoring,devops,database,innodb,processlist,replication,web-ui,fastapi
Classifier: Development Status :: 4 - Beta
Classifier: Intended Audience :: Developers
Classifier: Intended Audience :: System Administrators
Classifier: Topic :: Database
Classifier: Topic :: System :: Monitoring
Classifier: Topic :: System :: Systems Administration
Classifier: Topic :: Utilities
Classifier: License :: OSI Approved :: MIT License
Classifier: Programming Language :: Python :: 3
Classifier: Programming Language :: Python :: 3.10
Classifier: Programming Language :: Python :: 3.11
Classifier: Programming Language :: Python :: 3.12
Classifier: Programming Language :: Python :: 3.13
Classifier: Operating System :: OS Independent
Classifier: Framework :: FastAPI
Classifier: Environment :: Web Environment
Requires-Python: >=3.10
License-File: LICENSE
Requires-Dist: fastapi>=0.109.0
Requires-Dist: uvicorn[standard]>=0.27.0
Requires-Dist: sqlalchemy>=2.0.36
Requires-Dist: pyyaml>=6.0.1
Requires-Dist: jinja2>=3.1.3
Requires-Dist: python-multipart>=0.0.6
Requires-Dist: aiofiles>=23.2.1
Requires-Dist: pymysql>=1.1.0
Requires-Dist: cryptography
Dynamic: license-file
